{
    "fxname": "V-Syn",
    "fxid": "0xc0",
    "gid": "0x7",
    "version": "1.00",
    "Parameters": [
        {
            "name": "Decay",
            "mmax": 100,
            "mdefault": 24,
            "pedal": true
        },
        {
            "name": "Sense",
            "mmax": 30,
            "mdefault": 11,
            "pedal": false
        },
        {
            "name": "Range",
            "mmax": 19,
            "mdefault": 17,
            "pedal": false
        },
        {
            "name": "Synth",
            "mmax": 100,
            "mdefault": 100,
            "pedal": true
        },
        {
            "name": "Dry",
            "mmax": 100,
            "mdefault": 80,
            "pedal": true
        },
        {
            "name": "Level",
            "mmax": 150,
            "mdefault": 100,
            "pedal": true
        }
    ]
}